pytest_yapf.py
pytest_yapf-0.1.1.dist-info/DESCRIPTION.rst
pytest_yapf-0.1.1.dist-info/entry_points.txt
pytest_yapf-0.1.1.dist-info/METADATA
pytest_yapf-0.1.1.dist-info/metadata.json
pytest_yapf-0.1.1.dist-info/RECORD
pytest_yapf-0.1.1.dist-info/top_level.txt
pytest_yapf-0.1.1.dist-info/WHEEL
