Metadata-Version: 2.0
Name: pytest-yapf
Version: 0.1.1
Summary: Run yapf
Home-page: https://github.com/django-stars/pytest-yapf
Author: Roman Osipenko
Author-email: roman.osipenko@djangostars.com
License: MIT
Platform: UNKNOWN
Classifier: Development Status :: 4 - Beta
Classifier: Framework :: Pytest
Classifier: Intended Audience :: Developers
Classifier: Topic :: Software Development :: Testing
Classifier: Programming Language :: Python
Classifier: Programming Language :: Python :: 2
Classifier: Programming Language :: Python :: 2.7
Classifier: Programming Language :: Python :: 3
Classifier: Programming Language :: Python :: 3.6
Classifier: Programming Language :: Python :: Implementation :: CPython
Classifier: Operating System :: OS Independent
Classifier: License :: OSI Approved :: MIT License
Requires-Dist: pytest (>=3.1.1)
Requires-Dist: yapf (>=0.16.2)
